LICENSE.txt
MANIFEST.in
README.rst
setup.py
cmsplugin_svg/__init__.py
cmsplugin_svg/cms_plugins.py
cmsplugin_svg/models.py
cmsplugin_svg.egg-info/PKG-INFO
cmsplugin_svg.egg-info/SOURCES.txt
cmsplugin_svg.egg-info/dependency_links.txt
cmsplugin_svg.egg-info/not-zip-safe
cmsplugin_svg.egg-info/requires.txt
cmsplugin_svg.egg-info/top_level.txt
cmsplugin_svg/migrations/0001_initial.py
cmsplugin_svg/migrations/0002_auto_20161017_1706.py
cmsplugin_svg/migrations/0003_auto_20161017_1750.py
cmsplugin_svg/migrations/0004_auto_20161017_1832.py
cmsplugin_svg/migrations/__init__.py
cmsplugin_svg/templates/cmsplugin_svg/plugin.html